hyperdock_llamaindex/__init__.py
hyperdock_llamaindex/dock.py
hyperdock_llamaindex-0.3.7.dist-info/METADATA
hyperdock_llamaindex-0.3.7.dist-info/WHEEL
hyperdock_llamaindex-0.3.7.dist-info/RECORD
