Metadata-Version: 2.4
Name: hyperdock-llamaindex
Version: 0.3.7
Summary: hyperdock-llamaindex
Author-email: Hyperpocket Team <hyperpocket@vessl.ai>
Requires-Python: >=3.11
Requires-Dist: hyperpocket
Requires-Dist: hyperpocket-llamaindex
Requires-Dist: llama-index-tools-duckduckgo
Requires-Dist: llama-index-tools-google
Requires-Dist: llama-index-tools-slack
Requires-Dist: llama-index>=0.12.14
Requires-Dist: multiprocess>=0.70.16
Requires-Dist: slack-sdk
